chargily_lib/__init__.py
chargily_lib/constant.py
chargily_lib/invoice.py
chargily_lib/utils.py
chargily_lib/async_lib/__init__.py
chargily_lib/async_lib/webhook.py
chargily_epay_Async-0.0.2.dist-info/LICENSE
chargily_epay_Async-0.0.2.dist-info/METADATA
chargily_epay_Async-0.0.2.dist-info/WHEEL
chargily_epay_Async-0.0.2.dist-info/top_level.txt
chargily_epay_Async-0.0.2.dist-info/RECORD
