Metadata-Version: 2.1
Name: chargily-epay-Async
Version: 0.0.2
Summary: Chargily ePay Gateway (Python Library)
Home-page: https://github.com/Chargily/chargily-epay-python
Author: Chargily
Author-email: developers@chargily.com
Project-URL: Bug Reports, https://github.com/Chargily/chargily-epay-python/issues
Project-URL: Say Thanks!, https://github.com/Chargily
Project-URL: Source, https://github.com/Chargily/chargily-epay-python/
Project-URL: Website, https://chargily.com/
Keywords: e-pay,chargily,edahabia,cib
Classifier: Development Status :: 3 - Alpha
Classifier: Intended Audience :: Developers
Classifier: Topic :: Software Development :: Build Tools
Classifier: License :: OSI Approved :: MIT License
Classifier: Programming Language :: Python :: 3
Classifier: Programming Language :: Python :: 3.7
Classifier: Programming Language :: Python :: 3.8
Classifier: Programming Language :: Python :: 3.9
Classifier: Programming Language :: Python :: 3.10
Classifier: Programming Language :: Python :: 3 :: Only
Requires-Python: >=3.7
License-File: LICENSE
Requires-Dist: aiohttp (==3.8)
